{"Cheeks For Chairman":{"Business":null,"Candidate":340.0,"Corporate Sponsored PAC":null,"Corporation":null,"Individual":null,"Labor":null,"Labor Sponsored PAC":null,"Other":null,"Partnership":null},"Friends of Calvin Gurley 2012":{"Business":null,"Candidate":2387.27,"Corporate Sponsored PAC":null,"Corporation":null,"Individual":null,"Labor":null,"Labor Sponsored PAC":null,"Other":null,"Partnership":null},"Mendelson For Chairman":{"Business":21429.0,"Candidate":1000.0,"Corporate Sponsored PAC":21750.0,"Corporation":66080.0,"Individual":116673.55,"Labor":20100.0,"Labor Sponsored PAC":10000.0,"Other":268452.03,"Partnership":6500.0}}